conveyorbelt/__init__.py
conveyorbelt/__main__.py
conveyorbelt/utils.py
conveyorbelt/worker.py
conveyorbelt/commands/__init__.py
conveyorbelt/commands/cmd_assay_status.py
conveyorbelt/commands/cmd_check_flowcell.py
conveyorbelt/commands/cmd_config.py
conveyorbelt/commands/cmd_cov.py
conveyorbelt/commands/cmd_describe_host.py
conveyorbelt/commands/cmd_flake8.py
conveyorbelt/commands/cmd_flow_cell_positions.py
conveyorbelt/commands/cmd_glue_community.py
conveyorbelt/commands/cmd_glue_reports.py
conveyorbelt/commands/cmd_hpc.py
conveyorbelt/commands/cmd_import.py
conveyorbelt/commands/cmd_info.py
conveyorbelt/commands/cmd_metadata.py
conveyorbelt/commands/cmd_phe.py
conveyorbelt/commands/cmd_post_process.py
conveyorbelt/commands/cmd_primary_analysis.py
conveyorbelt/commands/cmd_sequence.py
conveyorbelt/commands/cmd_transfer_data.py
conveyorbelt/commands/cmd_upload.py
conveyorbelt-0.0.3.dist-info/LICENSE
conveyorbelt-0.0.3.dist-info/METADATA
conveyorbelt-0.0.3.dist-info/WHEEL
conveyorbelt-0.0.3.dist-info/entry_points.txt
conveyorbelt-0.0.3.dist-info/top_level.txt
conveyorbelt-0.0.3.dist-info/RECORD
