Metadata-Version: 2.1
Name: conveyorbelt
Version: 0.0.3
Summary: Command line interface for the CONVEYOR laboratory information management system (LIMS)
Home-page: https://github.com/sheffield-bioinformatics-core/conveyor-belt
Author: Joe Heffer
Author-email: j.heffer@sheffield.ac.uk
License: UNKNOWN
Platform: UNKNOWN
Classifier: Programming Language :: Python :: 3
Classifier: License :: OSI Approved :: MIT License
Classifier: Operating System :: OS Independent
Requires-Python: >=3.6
Requires-Dist: requests (~=2.25)
Requires-Dist: click (~=7.1)
